glean_requests/__init__.py
glean_requests/glean_client.py
glean_requests-0.3.0.dist-info/METADATA
glean_requests-0.3.0.dist-info/WHEEL
glean_requests-0.3.0.dist-info/licenses/LICENSE
glean_requests-0.3.0.dist-info/RECORD
