Metadata-Version: 2.4
Name: glean-requests
Version: 0.3.0
Summary: A minimal wrapper of the requests library for Glean's API
Project-URL: Homepage, https://github.com/johnagan/glean-requests
Project-URL: Bug Tracker, https://github.com/johnagan/glean-requests/issues
Author-email: John Agan <johnagan@gmail.com>
License: MIT
License-File: LICENSE
Keywords: api,client,glean,rest
Classifier: Development Status :: 4 - Beta
Classifier: Intended Audience :: Developers
Classifier: License :: OSI Approved :: MIT License
Classifier: Programming Language :: Python :: 3
Classifier: Programming Language :: Python :: 3.8
Classifier: Programming Language :: Python :: 3.9
Classifier: Programming Language :: Python :: 3.10
Classifier: Programming Language :: Python :: 3.11
Classifier: Programming Language :: Python :: 3.12
Classifier: Topic :: Software Development :: Libraries :: Python Modules
Requires-Python: >=3.8
Requires-Dist: requests>=2.32.0
